[
  {
    "variation": "default-slice",
    "name": "Default slice",
    "slice_type": "contact_section_split_two_tone",
    "items": [
      {
        "field": "recontextualize enterprise schemas",
        "fieldPlaceholder": "orchestrate mission-critical experiences"
      },
      {
        "field": "enable dynamic markets",
        "fieldPlaceholder": "streamline intuitive markets"
      },
      {
        "field": "brand robust web services",
        "fieldPlaceholder": "incentivize sticky systems"
      },
      {
        "field": "expedite rich infomediaries",
        "fieldPlaceholder": "brand bleeding-edge networks"
      },
      {
        "field": "leverage interactive blockchains",
        "fieldPlaceholder": "redefine leading-edge users"
      }
    ],
    "primary": {
      "title": [
        {
          "type": "paragraph",
          "text": "Reprehenderit in nulla cupidatat esse nostrud tempor est reprehenderit.",
          "spans": []
        }
      ],
      "description": [
        {
          "type": "paragraph",
          "text": "Id ad nisi do excepteur ullamco. Aliqua quis nisi mollit elit eu. Dolor amet esse consequat aliqua ut nostrud adipisicing nostrud ea ipsum duis laboris.",
          "spans": []
        }
      ],
      "address": [
        {
          "type": "paragraph",
          "text": "Laborum amet elit qui elit minim sit irure. Sunt tempor id tempor tempor cillum duis amet sunt ad quis deserunt. Minim cillum culpa commodo tempor enim voluptate.",
          "spans": []
        }
      ],
      "phone": "monetize intuitive solutions",
      "email": "scale one-to-one partnerships",
      "careerText": [
        {
          "type": "paragraph",
          "text": "Deserunt quis non aute. Tempor occaecat sint nisi est veniam esse. Officia aliqua dolore ullamco nulla anim qui fugiat officia exercitation deserunt anim commodo occaecat do consectetur.",
          "spans": []
        }
      ],
      "careerLink": {
        "link_type": "Web",
        "url": "https://slicemachine.dev"
      },
      "CareerLinkText": "exploit user-centric models",
      "cta": "envisioneer mission-critical channels"
    }
  }
]