[
  {
    "variation": "default-slice",
    "name": "Default slice",
    "slice_type": "category_preview_with_image_backgrounds",
    "items": [],
    "primary": {
      "title": [
        {
          "type": "heading1",
          "text": "Exploit innovative niches",
          "spans": []
        }
      ],
      "linkLabel": "incubate compelling deliverables",
      "link": {
        "link_type": "Web",
        "url": "https://prismic.io"
      },
      "imageLeft": {
        "dimensions": {
          "width": 592,
          "height": 592
        },
        "alt": "Placeholder image",
        "copyright": null,
        "url": "https://images.unsplash.com/photo-1587653915936-5623ea0b949a?w=592&h=592&fit=crop",
        "mobile": {
          "dimensions": {
            "width": 560,
            "height": 280
          },
          "alt": "Placeholder image",
          "copyright": null,
          "url": "https://images.unsplash.com/photo-1587653915936-5623ea0b949a?w=560&h=280&fit=crop"
        }
      },
      "imageLeftTitle": "leverage transparent partnerships",
      "imageLeftCta": "e-enable front-end systems",
      "imageTopRight": {
        "dimensions": {
          "width": 592,
          "height": 280
        },
        "alt": "Placeholder image",
        "copyright": null,
        "url": "https://images.unsplash.com/photo-1587840171670-8b850147754e?w=592&h=280&fit=crop",
        "mobile": {
          "dimensions": {
            "width": 560,
            "height": 280
          },
          "alt": "Placeholder image",
          "copyright": null,
          "url": "https://images.unsplash.com/photo-1587840171670-8b850147754e?w=560&h=280&fit=crop"
        }
      },
      "imageTopRightTitle": "incubate clicks-and-mortar convergence",
      "imageTopRightCta": "engineer extensible bandwidth",
      "imageBottomRight": {
        "dimensions": {
          "width": 592,
          "height": 280
        },
        "alt": "Placeholder image",
        "copyright": null,
        "url": "https://images.unsplash.com/photo-1525547719571-a2d4ac8945e2?w=592&h=280&fit=crop",
        "mobile": {
          "dimensions": {
            "width": 560,
            "height": 280
          },
          "alt": "Placeholder image",
          "copyright": null,
          "url": "https://images.unsplash.com/photo-1525547719571-a2d4ac8945e2?w=560&h=280&fit=crop"
        }
      },
      "imageBottomRightTitle": "generate end-to-end partnerships",
      "imageBottomRightCta": "incentivize revolutionary solutions"
    }
  }
]